MANIFEST.in
VERSION
setmeup.py
setup.cfg
setup.py
setmeup.egg-info/PKG-INFO
setmeup.egg-info/SOURCES.txt
setmeup.egg-info/dependency_links.txt
setmeup.egg-info/top_level.txt