Metadata-Version: 1.1
Name: setmeup
Version: 0.1.5
Summary: Runtime settings for minimalists
Home-page: https://github.com/szastupov/setmeup
Author: Stepan Zastupov
Author-email: stepan.zastupov@gmail.com
License: MIT
Keywords: environ settings env config
Platform: UNKNOWN
Classifier: Development Status :: 4 - Beta
Classifier: Intended Audience :: Developers
Classifier: License :: OSI Approved :: MIT License
Classifier: Topic :: Software Development
Classifier: Topic :: Software Development :: Libraries
